gdml/__init__.py
gdml/DL/__init__.py
gdml/DL/dl.py
gdml/Data/__init__.py
gdml/Data/read_data.py
gdml/ML/__init__.py
gdml/ML/ml.py
gdml-1.5.0.dist-info/licenses/LICENSE
gdml-1.5.0.dist-info/METADATA
gdml-1.5.0.dist-info/WHEEL
gdml-1.5.0.dist-info/top_level.txt
gdml-1.5.0.dist-info/RECORD
