Metadata-Version: 2.4
Name: gdml
Version: 1.5.0
Summary: A machine learning and deep learning utilities library.
Home-page: https://github.com/gokulraj0906/gdml
Author: Gokulraj S
Author-email: Gokulraj S <gokulsenthil0906@gmail.com>
License: Apache-2.0
Project-URL: Homepage, https://github.com/gokulraj0906/gdml
Project-URL: Bug Tracker, https://github.com/gokulraj0906/gdml/issues
Classifier: Programming Language :: Python :: 3
Classifier: License :: OSI Approved :: Apache Software License
Classifier: Operating System :: OS Independent
Requires-Python: >=3.8
License-File: LICENSE
Requires-Dist: scikit-learn
Requires-Dist: xgboost
Requires-Dist: pandas
Requires-Dist: gymnasium
Requires-Dist: numpy
Requires-Dist: opencv-python
Requires-Dist: Pillow
Requires-Dist: matplotlib
Requires-Dist: seaborn
Requires-Dist: statsmodels
Requires-Dist: prophet
Requires-Dist: scipy
Requires-Dist: catboost
Requires-Dist: lightgbm
Requires-Dist: joblib
Requires-Dist: torch
Requires-Dist: torchvision
Dynamic: author
Dynamic: home-page
Dynamic: license-file
Dynamic: requires-python
